easy_db/__init__.py
easy_db/db.py
dm_easy_db-0.1.1.dist-info/METADATA
dm_easy_db-0.1.1.dist-info/WHEEL
dm_easy_db-0.1.1.dist-info/top_level.txt
dm_easy_db-0.1.1.dist-info/RECORD
