Metadata-Version: 2.1
Name: dm-easy-db
Version: 0.1.1
Summary: A easy common db operation package
Home-page: http://gitlab.admin.bluemoon.com.cn/BigData-DataAlgorithm/easy_db.git
Author: miaodongfang
Author-email: miaodongfang@bluemoon.com.cn
License: UNKNOWN
Platform: UNKNOWN
Classifier: Programming Language :: Python :: 3
Classifier: Operating System :: OS Independent
Requires-Python: >=3.6
